dcc_mcp_rpyc/__init__.py
dcc_mcp_rpyc/action_adapter.py
dcc_mcp_rpyc/adapter/__init__.py
dcc_mcp_rpyc/adapter/base.py
dcc_mcp_rpyc/adapter/dcc.py
dcc_mcp_rpyc/adapter/session.py
dcc_mcp_rpyc/application/__init__.py
dcc_mcp_rpyc/application/adapter.py
dcc_mcp_rpyc/application/client.py
dcc_mcp_rpyc/application/service.py
dcc_mcp_rpyc/client/__init__.py
dcc_mcp_rpyc/client/async_base.py
dcc_mcp_rpyc/client/async_dcc.py
dcc_mcp_rpyc/client/base.py
dcc_mcp_rpyc/client/dcc.py
dcc_mcp_rpyc/client/pool.py
dcc_mcp_rpyc/discovery/__init__.py
dcc_mcp_rpyc/discovery/base.py
dcc_mcp_rpyc/discovery/factory.py
dcc_mcp_rpyc/discovery/file_strategy.py
dcc_mcp_rpyc/discovery/registry.py
dcc_mcp_rpyc/discovery/zeroconf_strategy.py
dcc_mcp_rpyc/server/__init__.py
dcc_mcp_rpyc/server/base.py
dcc_mcp_rpyc/server/dcc.py
dcc_mcp_rpyc/server/decorators.py
dcc_mcp_rpyc/server/discovery.py
dcc_mcp_rpyc/server/factory.py
dcc_mcp_rpyc/server/lifecycle.py
dcc_mcp_rpyc/server/server_utils.py
dcc_mcp_rpyc/testing/__init__.py
dcc_mcp_rpyc/testing/mock_services.py
dcc_mcp_rpyc/utils/__init__.py
dcc_mcp_rpyc/utils/decorators.py
dcc_mcp_rpyc/utils/di.py
dcc_mcp_rpyc/utils/errors.py
dcc_mcp_rpyc/utils/rpyc_utils.py
dcc_mcp_rpyc-0.4.0.dist-info/entry_points.txt
dcc_mcp_rpyc-0.4.0.dist-info/LICENSE
dcc_mcp_rpyc-0.4.0.dist-info/METADATA
dcc_mcp_rpyc-0.4.0.dist-info/WHEEL
dcc_mcp_rpyc-0.4.0.dist-info/RECORD
