Metadata-Version: 2.3
Name: dcc-mcp-rpyc
Version: 0.4.0
Summary: RPYC implementation for DCC software integration with Model Context Protocol
License: MIT
Author: Long Hao
Author-email: hal.long@outlook.com
Requires-Python: >=3.7,<4.0
Classifier: Development Status :: 3 - Alpha
Classifier: Intended Audience :: Developers
Classifier: License :: OSI Approved :: MIT License
Classifier: Programming Language :: Python :: 3
Classifier: Programming Language :: Python :: 3.7
Classifier: Programming Language :: Python :: 3.8
Classifier: Programming Language :: Python :: 3.9
Classifier: Programming Language :: Python :: 3.10
Classifier: Programming Language :: Python :: 3.11
Classifier: Programming Language :: Python :: 3.12
Classifier: Programming Language :: Python :: 3.13
Requires-Dist: dcc-mcp-core (>=0.5.0,<0.6.0)
Requires-Dist: rpyc (>=6.0.0,<7.0.0)
Requires-Dist: zeroconf (>=0.38.0,<0.132.0)
Project-URL: Homepage, https://github.com/loonghao/dcc-mcp-rpyc
Project-URL: Issues, https://github.com/loonghao/dcc-mcp-rpyc/issues
